stevesie/__init__.py
stevesie/config.py
stevesie/remote_resource.py
stevesie/remote_resource_sequence.py
stevesie/resources/__init__.py
stevesie/resources/active_proxies.py
stevesie/resources/proxies.py
stevesie/resources/proxy.py
stevesie/resources/task.py
stevesie/resources/task_collection.py
stevesie/resources/task_collection_field.py
stevesie/resources/task_collection_result.py
stevesie/resources/task_collection_result_set.py
stevesie/resources/task_dependency.py
stevesie/resources/worker.py
stevesie/resources/worker_collection_results.py
stevesie/resources/workflow.py
stevesie/resources/workflow_parameter.py
stevesie/resources/workflow_task.py
stevesie/services/__init__.py
stevesie/services/worker_service.py
stevesie/utils/__init__.py
stevesie/utils/api.py
stevesie-0.0.7.dist-info/LICENSE.txt
stevesie-0.0.7.dist-info/METADATA
stevesie-0.0.7.dist-info/RECORD
stevesie-0.0.7.dist-info/WHEEL
stevesie-0.0.7.dist-info/top_level.txt
tests/__init__.py
tests/conftest.py
tests/test_worker.py
