Metadata-Version: 2.1
Name: stevesie
Version: 0.0.7
Summary: Stevesie Python Client.
Home-page: https://github.com/stevesie/stevesie-py
Author: Stevesie, LLC
Author-email: steve@stevesie.com
License: UNKNOWN
Platform: UNKNOWN
Classifier: Programming Language :: Python :: 3
Classifier: License :: OSI Approved :: MIT License
Classifier: Operating System :: OS Independent
Requires-Dist: inflection (<1.0,>=0.2.0)
Requires-Dist: python-dateutil (<3.0,>=2.0)
Requires-Dist: requests (<3.0,>=0.11.1)
